task_4/verify/memory.v
module memory(ADDR,RDBUS, WDBUS,RD,WR,CLK,RST,RESULT);
input [15:0] ADDR;
input [15:0] WDBUS;
input RD,WR,CLK,RST;
output [15:0] RDBUS;
output [15:0] RESULT;

reg [15:0] MEM [65536:0];

integer ii;
//reg [15:0] DBUS_TMP;

//wire [15:0] dato;

always @ (posedge CLK) begin
	if(!RST)begin
		ii=0;
		MEM[16'h05AA] <= 16'b0000_1011_1111_0000; // dummy value
		MEM[ii] <= 16'b0000_000_0_000_000_00; ii=ii+1;//nothing
		
		MEM[ii] <= 16'b0011_000_0_00010000; ii=ii+1;//load l: loads 0x10
		MEM[ii] <= 16'b0011_001_1_00101001; ii=ii+1;//load h: loads 0x29
		
		MEM[ii] <= 16'b0110_010_0_000_001_00; ii=ii+1;//or operation to generate 0x2910 and store it in register 2

		MEM[ii] <= 16'b0011_000_0_10101010; ii=ii+1;//load l: loads 0xAA to reg0
		MEM[ii] <= 16'b0011_001_1_00000101; ii=ii+1;//load h: loads 0x05 to reg1
		MEM[ii] <= 16'b0110_011_0_000_001_00; ii=ii+1;// or operation to generate 0x05AA and store it in register 3

		MEM[ii] <= 16'b0000_100_0_010_011_00; ii=ii+1;// add reg2 and reg3 and store reg 4

		MEM[ii] <= 16'b0010_000_0_011_100_00; ii=ii+1;// stroe reg4 to mem location 0x05AA
		
		
	end else begin
		if(WR) MEM[ADDR]<=WDBUS;
	end
end


assign RDBUS = (RD)? MEM[ADDR] : 16'b0000_0000_0000_0000;
assign RESULT = MEM[16'h05AA]; //Is only used to view the result in waveform

endmodule

lab_04_final/verify/memory_tb.v
`timescale 1ns/1ps

module memory_tb;


reg [15:0] ADDR;
reg [15:0] WDBUS;
reg RD,WR,CLK,RST;
wire [15:0] RDBUS;
wire [15:0] RESULT;

memory uut(.ADDR(ADDR), .RDBUS(RDBUS), .WDBUS(WDBUS), .RD(RD), .WR(WR), .CLK(CLK), .RST(RST), .RESULT(RESULT));


integer i;
initial begin
    $dumpfile("memory_tb.vcd");
    $dumpvars(0, memory_tb);
    CLK = 0;
    RST = 0;
    WDBUS = 0;
    ADDR = 0;
    RD = 0;
    WR = 0;
    #10;
    RST = 1;
    #10;
    RD = 1;
    for (i = 0; i < 10; i++) begin
        ADDR = i;
        #10;
    end
    RD = 0;
    #100;

    $finish;
end


always begin
    #5 CLK <= ~CLK;
end
    
endmodule

lab_04_final/verify/memory_tb.vcd
$date
	Wed Jul 29 10:25:15 2020
$end
$version
	Icarus Verilog
$end
$timescale
	1ps
$end
$scope module memory_tb $end
$var wire 16 ! RESULT [15:0] $end
$var wire 16 " RDBUS [15:0] $end
$var reg 16 # ADDR [15:0] $end
$var reg 1 $ CLK $end
$var reg 1 % RD $end
$var reg 1 & RST $end
$var reg 16 ' WDBUS [15:0] $end
$var reg 1 ( WR $end
$var integer 32 ) i [31:0] $end
$scope module uut $end
$var wire 16 * ADDR [15:0] $end
$var wire 1 $ CLK $end
$var wire 1 % RD $end
$var wire 16 + RESULT [15:0] $end
$var wire 1 & RST $end
$var wire 16 , WDBUS [15:0] $end
$var wire 1 ( WR $end
$var wire 16 - RDBUS [15:0] $end
$var integer 32 . ii [31:0] $end
$upscope $end
$upscope $end
$enddefinitions $end
#0
$dumpvars
bx .
b0 -
b0 ,
bx +
b0 *
bx )
0(
b0 '
0&
0%
0$
b0 #
b0 "
bx !
$end
#5000
b101111110000 !
b101111110000 +
b1001 .
1$
#10000
0$
1&
#15000
1$
#20000
0$
b0 )
1%
#25000
1$
#30000
0$
b11000000010000 "
b11000000010000 -
b1 #
b1 *
b1 )
#35000
1$
#40000
0$
b11001100101001 "
b11001100101001 -
b10 #
b10 *
b10 )
#45000
1$
#50000
0$
b110010000000100 "
b110010000000100 -
b11 #
b11 *
b11 )
#55000
1$
#60000
0$
b11000000000101 "
b11000000000101 -
b100 #
b100 *
b100 )
#65000
1$
#70000
0$
b11001110101010 "
b11001110101010 -
b101 #
b101 *
b101 )
#75000
1$
#80000
0$
b110011000000100 "
b110011000000100 -
b110 #
b110 *
b110 )
#85000
1$
#90000
0$
b100001001100 "
b100001001100 -
b111 #
b111 *
b111 )
#95000
1$
#100000
0$
b10000001110000 "
b10000001110000 -
b1000 #
b1000 *
b1000 )
#105000
1$
#110000
0$
bx "
bx -
b1001 #
b1001 *
b1001 )
#115000
1$
#120000
0$
b0 "
b0 -
0%
b1010 )
