dflipflop/verify/dflipflop.v
module dflipflop (input d,clk,reset, output q);
reg q;

always @ (posedge clk)
begin
    if (reset)
        q<=1'b0;
    else
        q<=d;
end
        
        
endmodule

dflipflop/verify/dflipflop_tb.v
`timescale 1ns/1ps

module dflipflop_tb;
//inputs
    reg d, clk, reset;
    wire q;
    dflipflop test_unit(.d(d), .clk(clk), .reset(reset), .q(q));
    always 
    #5 clk = ~clk;
    
    integer i;
initial
begin
    $dumpfile("dflipflop.vcd"); //generate a waveform call it x.vcd and dump the files there
    $dumpvars(0, dflipflop_tb);
    clk = 0;
    d = 1'b0;
    reset = 1'b0;
    for (i=0; i<25; i++)
        begin
        d = ~d;
        #2;
        end
    $finish;
end

endmodule

dflipflop/verify/dflipflop.vcd
$date
	Thu May  7 18:46:14 2020
$end
$version
	Icarus Verilog
$end
$timescale
	1ps
$end
$scope module dflipflop_tb $end
$var wire 1 ! q $end
$var reg 1 " clk $end
$var reg 1 # d $end
$var reg 1 $ reset $end
$var integer 32 % i [31:0] $end
$scope module test_unit $end
$var wire 1 " clk $end
$var wire 1 # d $end
$var wire 1 $ reset $end
$var reg 1 ! q $end
$upscope $end
$upscope $end
$enddefinitions $end
#0
$dumpvars
b0 %
0$
1#
0"
x!
$end
#2000
0#
b1 %
#4000
1#
b10 %
#5000
1!
1"
#6000
0#
b11 %
#8000
1#
b100 %
#10000
0#
b101 %
0"
#12000
1#
b110 %
#14000
0#
b111 %
#15000
0!
1"
#16000
1#
b1000 %
#18000
0#
b1001 %
#20000
1#
b1010 %
0"
#22000
0#
b1011 %
#24000
1#
b1100 %
#25000
1!
1"
#26000
0#
b1101 %
#28000
1#
b1110 %
#30000
0#
b1111 %
0"
#32000
1#
b10000 %
#34000
0#
b10001 %
#35000
0!
1"
#36000
1#
b10010 %
#38000
0#
b10011 %
#40000
1#
b10100 %
0"
#42000
0#
b10101 %
#44000
1#
b10110 %
#45000
1!
1"
#46000
0#
b10111 %
#48000
1#
b11000 %
#50000
b11001 %
0"
