task_1_alu/verify/task_1_alu.v
module alu (input [15:0] a,b, 
            input [3:0] op_code, 
            output [15:0] alu_output, 
            output carryout,
            output zero_flag);
        
        reg [15:0] alu_result;
        reg zero_flag;
        wire [16:0] tmp;
        assign alu_output = alu_result;
        assign tmp = {1'b0,a} + {1'b0,b}; //this is for keeping carryout low
        assign carryout = tmp[16];
always @ (*)
    begin
    
        case(op_code)
            4'b0000:
            alu_result = a+b;
            4'b0100:
            alu_result = a^b;
            4'b0110:
            alu_result = a|b;
            4'b0111:
            alu_result = a&b;
            4'b1000: //LSB is one when A and B are equal
            if (a==b)
                alu_result = 16'h0001;
            4'b1001: //
            if (a!=b)
                alu_result = 16'h0001;
            4'b1010:
            alu_result = a-b;
            4'b1100: //LSB is one when A is less than B(signed)
            if($signed(a) < $signed(b))
                alu_result = 16'h0001;
            4'b1101:
            if($signed(a) >= $signed(b))
                alu_result = 16'h0001;
            4'b1110:
            if(a < b)
                alu_result = 16'h0001;
            4'b1111:
            if(a >= b)
                alu_result = 16'h0001;
            
            default: alu_result = 0;
        endcase
       
        if (alu_result == 16'h0000)
            zero_flag = 1'b1;
        else if (alu_result != 16'h0000)
            zero_flag = 1'b0;
    end


endmodule

task_1_alu/verify/task_1_alu_tb.v
`timescale 1ns/1ps

module alu_tb;
//inputs
    reg [15:0] a,b;
    reg [3:0] op_code;
    //outputs
    wire [15:0] alu_output;
    wire carryout;
    wire zero_flag;
    integer i;
    alu test_unit(.a(a),.b(b),.op_code(op_code),.alu_output(alu_output),.carryout(carryout),.zero_flag(zero_flag));

initial
begin
    $dumpfile("task_1_alu.vcd"); //generate a waveform call it x.vcd and dump the files there
    $dumpvars(0, alu_tb);
    a = 16'h0005;
    b = 16'h0004;
    op_code = 4'h0;
    for (i=0; i<16; i++) //testing for all the op-codes
        begin
        op_code = op_code+1;
        #10;
        end
        $finish;
end

endmodule

task_1_alu/verify/task_1_alu.vcd
$date
	Sun May 10 18:38:42 2020
$end
$version
	Icarus Verilog
$end
$timescale
	1ps
$end
$scope module alu_tb $end
$var wire 1 ! zero_flag $end
$var wire 1 " carryout $end
$var wire 16 # alu_output [15:0] $end
$var reg 16 $ a [15:0] $end
$var reg 16 % b [15:0] $end
$var reg 4 & op_code [3:0] $end
$var integer 32 ' i [31:0] $end
$scope module test_unit $end
$var wire 16 ( a [15:0] $end
$var wire 16 ) alu_output [15:0] $end
$var wire 16 * b [15:0] $end
$var wire 4 + op_code [3:0] $end
$var wire 17 , tmp [16:0] $end
$var wire 1 " carryout $end
$var reg 16 - alu_result [15:0] $end
$var reg 1 ! zero_flag $end
$upscope $end
$upscope $end
$enddefinitions $end
#0
$dumpvars
b0 -
b1001 ,
b1 +
b100 *
b0 )
b101 (
b0 '
b1 &
b100 %
b101 $
b0 #
0"
1!
$end
#10000
b10 &
b10 +
b1 '
#20000
b11 &
b11 +
b10 '
#30000
0!
b1 #
b1 )
b1 -
b100 &
b100 +
b11 '
#40000
1!
b0 #
b0 )
b0 -
b101 &
b101 +
b100 '
#50000
0!
b101 #
b101 )
b101 -
b110 &
b110 +
b101 '
#60000
b100 #
b100 )
b100 -
b111 &
b111 +
b110 '
#70000
b1000 &
b1000 +
b111 '
#80000
b1 #
b1 )
b1 -
b1001 &
b1001 +
b1000 '
#90000
b1010 &
b1010 +
b1001 '
#100000
1!
b0 #
b0 )
b0 -
b1011 &
b1011 +
b1010 '
#110000
b1100 &
b1100 +
b1011 '
#120000
0!
b1 #
b1 )
b1 -
b1101 &
b1101 +
b1100 '
#130000
b1110 &
b1110 +
b1101 '
#140000
b1111 &
b1111 +
b1110 '
#150000
b1001 #
b1001 )
b1001 -
b0 &
b0 +
b1111 '
#160000
b10000 '
